odoo10_addon_l10n_lu_mis_reports_tax-10.0.1.0.0.99.dev7-py2.7-nspkg.pth
odoo/addons/l10n_lu_mis_reports_tax/README.rst
odoo/addons/l10n_lu_mis_reports_tax/__init__.py
odoo/addons/l10n_lu_mis_reports_tax/__manifest__.py
odoo/addons/l10n_lu_mis_reports_tax/init_hooks.py
odoo/addons/l10n_lu_mis_reports_tax/data/account.account.tag-2015.csv
odoo/addons/l10n_lu_mis_reports_tax/data/account.tax.template-2015.xml
odoo/addons/l10n_lu_mis_reports_tax/data/mis_report_styles.xml
odoo/addons/l10n_lu_mis_reports_tax/data/mis_tax_analysis.xml
odoo/addons/l10n_lu_mis_reports_tax/i18n/l10n_lu_mis_reports_tax.pot
odoo/addons/l10n_lu_mis_reports_tax/scripts/gen_mis_tax_analysis.py
odoo/addons/l10n_lu_mis_reports_tax/static/description/icon.png
odoo10_addon_l10n_lu_mis_reports_tax-10.0.1.0.0.99.dev7.dist-info/DESCRIPTION.rst
odoo10_addon_l10n_lu_mis_reports_tax-10.0.1.0.0.99.dev7.dist-info/METADATA
odoo10_addon_l10n_lu_mis_reports_tax-10.0.1.0.0.99.dev7.dist-info/RECORD
odoo10_addon_l10n_lu_mis_reports_tax-10.0.1.0.0.99.dev7.dist-info/WHEEL
odoo10_addon_l10n_lu_mis_reports_tax-10.0.1.0.0.99.dev7.dist-info/metadata.json
odoo10_addon_l10n_lu_mis_reports_tax-10.0.1.0.0.99.dev7.dist-info/namespace_packages.txt
odoo10_addon_l10n_lu_mis_reports_tax-10.0.1.0.0.99.dev7.dist-info/top_level.txt
